[
    {
        "english": "PERFECT Lips, 10ml",
        "pidNo": "662449"
    },
    {
        "english": "Healthy Glow Lip Balm, 5g",
        "pidNo": "588380"
    },
    {
        "english": "Perfect Neck Cream, 60ml",
        "pidNo": "820816"
    },
    {
        "english": "Perfect Balancing Toner, 160ml",
        "pidNo": "820813"
    },
    {
        "english": "Perfect Sunscreen Broad Spectrum SPF50, 60ml ",
        "pidNo": "820818"
    },
    {
        "english": "Perfect Cleansing Foam, 125ml",
        "pidNo": "820812"
    },
    {
        "english": "Perfect Cleansing Scrub, 100ml",
        "pidNo": "820811"
    },
    {
        "english": "WW Cream, 60ml",
        "pidNo": "820815"
    },
    {
        "english": "Anti-Aging Eye Lift, 15ml",
        "pidNo": "786462"
    },
    {
        "english": "Super Cream, 50ml",
        "pidNo": "820814"
    },
    {
        "english": "WW Eye Cream, 15ml",
        "pidNo": "820817"
    },
    {
        "english": "Aqua BB SPF40 Broad Spectrum - 01 Light, 28g",
        "pidNo": "511653"
    },
    {
        "english": "Perfect Mask, 5 x 140ml",
        "pidNo": "588383"
    },
    {
        "english": "PERFECT Body Cream, 200ml",
        "pidNo": "662448"
    },
    {
        "english": "Perfect BB SPF40 Tinted Moisturizer - 1 Light, 45ml",
        "pidNo": "341920"
    },
    {
        "english": "Anti-Aging Cream, 60ml",
        "pidNo": "662447"
    },
    {
        "english": "Super Eye Treatment, 20ml",
        "pidNo": "548823"
    },
    {
        "english": "Super H Serum, 35ml",
        "pidNo": "548822"
    },
    {
        "english": "Aqua BB SPF40 Broad Spectrum - 02 Medium, 28g ",
        "pidNo": "511654"
    },
    {
        "english": "Perfect Lite Sunscreen SPF30, 100ml",
        "pidNo": "588385"
    },
    {
        "english": "Super Face Serum, 35ml",
        "pidNo": "548824"
    },
    {
        "english": "Perfect Cream, 60ml",
        "pidNo": "588384"
    },
    {
        "english": "Perfect Facial Wash, 200ml",
        "pidNo": "588381"
    },
    {
        "english": "M Cream Ultimate Lift, 60ml",
        "pidNo": "403015"
    },
    {
        "english": "Aqua BB SPF40 Broad Spectrum - 03 Dark, 28g",
        "pidNo": "511655"
    },
    {
        "english": "Perfect BB SPF40 Tinted Moisturizer - 2 Medium, 45ml",
        "pidNo": "341921"
    },
    {
        "english": "Perfect BB SPF40 Tinted Moisturizer - 3 Dark, 45ml",
        "pidNo": "341922"
    }
]