[
    {
        "english": "Elite Smoke Oval 8 Brush",
        "pidNo": "692674"
    },
    {
        "english": "Elite Smoke Oval 7 Brush",
        "pidNo": "749702"
    },
    {
        "english": "Elite Smoke Palm Brush",
        "pidNo": "901164"
    },
    {
        "english": "Fluenta 5 Brush Set",
        "pidNo": "903575"
    },
    {
        "english": "Elite Mirror Linear 3 Brush",
        "pidNo": "549007"
    },
    {
        "english": "Elite Gold Palm Brush",
        "pidNo": "864230"
    },
    {
        "english": "Elite Mirror Palm Brush",
        "pidNo": "808734"
    },
    {
        "english": "Elite Mirror 3 Brush Set",
        "pidNo": "549010"
    },
    {
        "english": "Fluenta Oval 8 Brush",
        "pidNo": "903566"
    },
    {
        "english": "Elite Mirror Oval 7 Brush",
        "pidNo": "678866"
    },
    {
        "english": "Elite Smoke Linear 6 Brush",
        "pidNo": "692670"
    },
    {
        "english": "Elite Smoke Linear 3 Brush",
        "pidNo": "692669"
    },
    {
        "english": "Fluenta Oval 7 Brush",
        "pidNo": "903567"
    },
    {
        "english": "Linear 6 Brush",
        "pidNo": "596467"
    },
    {
        "english": "Fluenta Oval 6 Brush",
        "pidNo": "903568"
    },
    {
        "english": "Fluenta Collection Compact Displayer",
        "pidNo": "903577"
    },
    {
        "english": "Elite Smoke 5 Brush Set",
        "pidNo": "676835"
    },
    {
        "english": "Elite Mirror Oval 6 Brush",
        "pidNo": "549005"
    },
    {
        "english": "Fluenta 9 Brush Set",
        "pidNo": "903576"
    },
    {
        "english": "Fluenta Oval 10 Brush",
        "pidNo": "903565"
    },
    {
        "english": "Fluenta Circle 1R Brush",
        "pidNo": "903573"
    },
    {
        "english": "Fluenta Oval 3 Brush",
        "pidNo": "903570"
    },
    {
        "english": "Premier Brush Cleaning Pad ",
        "pidNo": "659423"
    },
    {
        "english": "Fluenta Linear 3 Brush",
        "pidNo": "903571"
    },
    {
        "english": "Fluenta Circle 1 Brush",
        "pidNo": "903574"
    },
    {
        "english": "Fluenta Oval 4 Brush",
        "pidNo": "903569"
    },
    {
        "english": "Fluenta Linear 1 Brush",
        "pidNo": "903572"
    },
    {
        "english": "Digit Skincare Brush Set",
        "pidNo": "768171"
    },
    {
        "english": "Elite Mirror 5 Brush Set",
        "pidNo": "549011"
    },
    {
        "english": "Elite Mirror Oval 8 Brush",
        "pidNo": "596465"
    },
    {
        "english": "Elite Smoke 10 Brush Set",
        "pidNo": "676836"
    },
    {
        "english": "Elite Smoke Oval 6 Brush",
        "pidNo": "692673"
    },
    {
        "english": "Elite Smoke Linear 1 Brush",
        "pidNo": "692668"
    },
    {
        "english": "Elite Smoke Circle 1 Brush",
        "pidNo": "692666"
    },
    {
        "english": "Elite Mirror Linear 3 Demi Brush",
        "pidNo": "808733"
    },
    {
        "english": "Digit 10 Brush Set",
        "pidNo": "864236"
    },
    {
        "english": "Digit 5 Brush Set",
        "pidNo": "864234"
    },
    {
        "english": "Elite Mirror Circle 1 Brush",
        "pidNo": "549009"
    },
    {
        "english": "Elite Smoke Oval 4 Brush",
        "pidNo": "692672"
    },
    {
        "english": "Elite Mirror Linear 1 Brush",
        "pidNo": "549008"
    },
    {
        "english": "Elite Mirror 10 Brush Set",
        "pidNo": "549012"
    },
    {
        "english": "Textured-shell brush case",
        "pidNo": "659420"
    },
    {
        "english": "Elite Mirror Oval 3 Brush",
        "pidNo": "549006"
    },
    {
        "english": "Elite Mirror Linear 1 Demi Brush",
        "pidNo": "808732"
    },
    {
        "english": "Elite Smoke Collection Oval 10 Brush",
        "pidNo": "692675"
    },
    {
        "english": "Elite Collection Compact Brush Displayer",
        "pidNo": "763326"
    },
    {
        "english": "Elite Smoke Oval 3 Brush",
        "pidNo": "692671"
    },
    {
        "english": "Elite Smoke 3 Brush Set",
        "pidNo": "676834"
    },
    {
        "english": "Elite Smoke Circle 1R Brush",
        "pidNo": "692667"
    },
    {
        "english": "Elite Mirror Oval 4 Brush",
        "pidNo": "596466"
    },
    {
        "english": "Elite Mirror Oval 10 Brush",
        "pidNo": "549004"
    },
    {
        "english": "Elite Mirror Circle 1R Brush",
        "pidNo": "596468"
    },
    {
        "english": "Textured-shell brush case",
        "pidNo": "659421"
    },
    {
        "english": "Replacement Microfibre Cloths x 10",
        "pidNo": "659422"
    },
    {
        "english": "Elite Gold 10 Brush Set",
        "pidNo": "724209"
    },
    {
        "english": "Brush Cleansing Foam, 210ml",
        "pidNo": "549014"
    }
]