[
    {
        "english": "Travel Boar Bristle Hairbrush",
        "pidNo": "720565"
    },
    {
        "english": "Travel Mixed Bristle Hairbrush",
        "pidNo": "720567"
    },
    {
        "english": "Large Boar Bristle Hairbrush",
        "pidNo": "720564"
    },
    {
        "english": "Refresh Dry Shampoo, 102g",
        "pidNo": "578366"
    },
    {
        "english": "Large Mixed Bristle Hairbrush",
        "pidNo": "720566"
    },
    {
        "english": "Nourish Conditioner for Dry Hair, 300ml",
        "pidNo": "529204"
    },
    {
        "english": "Preserve Shampoo for Color Treated Hair, 300ml",
        "pidNo": "529206"
    },
    {
        "english": "Heal Mask for Damaged Hair, 300ml",
        "pidNo": "529209"
    },
    {
        "english": "Plump Thickening Mousse, 170g",
        "pidNo": "578365"
    },
    {
        "english": "Nourish Shampoo for Dry Hair, 300ml",
        "pidNo": "529203"
    },
    {
        "english": "Brilliance Hair Perfecting Oil, 120ml",
        "pidNo": "529210"
    },
    {
        "english": "Cure Hair Strengthening Split End Serum, 30ml",
        "pidNo": "614907"
    },
    {
        "english": "Smooth Heat Defense Style Cream - 120ml",
        "pidNo": "614908"
    },
    {
        "english": "Heal Shampoo for Damaged Hair, 300ml",
        "pidNo": "529208"
    },
    {
        "english": "Nourish Mask for Dry Hair, 300ml",
        "pidNo": "529205"
    },
    {
        "english": "Preserve Conditioner for Color Treated Hair, 300ml",
        "pidNo": "529207"
    },
    {
        "english": "Amplify Shampoo for Fine Hair, 300ml",
        "pidNo": "529201"
    },
    {
        "english": "Amplify Conditioner for Fine Hair, 300ml",
        "pidNo": "529202"
    }
]