[
    {
        "chinese": "牙膏三件套，3 x 75ml（香型：Royal，Karakum，Rambas）",
        "pidNo": "962667"
    },
    {
        "chinese": "世界奇观牙膏套装，3 x 25ml（香型：Royal，Karakum，Rambas）",
        "pidNo": "962668"
    },
    {
        "chinese": "美白牙膏，3 x 75ml",
        "pidNo": "647781"
    },
    {
        "chinese": "深邃黑牙刷（三支装）",
        "pidNo": "648419"
    },
    {
        "chinese": "经典强力薄荷、海洋薄荷和美白薄荷牙膏，3 x 75ml",
        "pidNo": "355157"
    },
    {
        "chinese": "肉桂薄荷、茉莉薄荷和生姜薄荷牙膏，25ml x 3 支 ",
        "pidNo": "699027"
    },
    {
        "chinese": "肉桂薄荷、茉莉薄荷和生姜薄荷牙膏，3 x 75ml",
        "pidNo": "355158"
    },
    {
        "chinese": "美白牙膏，3 x 25ml",
        "pidNo": "699028"
    },
    {
        "chinese": "经典强力薄荷、海洋薄荷和美白薄荷牙膏，3 x 25ml",
        "pidNo": "529223"
    },
    {
        "chinese": "多口味牙膏礼盒套装：甘草、薄荷、肉桂、经典、姜、茉莉和美白牙膏，7 x 25ml",
        "pidNo": "647782"
    },
    {
        "chinese": "强力薄荷浓缩漱口水，120ml",
        "pidNo": "529225"
    }
]